brume/__init__.py
brume/assets.py
brume/boto_client.py
brume/checker.py
brume/cli.py
brume/color.py
brume/config.py
brume/output.py
brume/stack.py
brume/template.py
brume-2.0.2.dist-info/LICENSE.txt
brume-2.0.2.dist-info/METADATA
brume-2.0.2.dist-info/WHEEL
brume-2.0.2.dist-info/entry_points.txt
brume-2.0.2.dist-info/top_level.txt
brume-2.0.2.dist-info/zip-safe
brume-2.0.2.dist-info/RECORD
