Metadata-Version: 2.1
Name: brume
Version: 2.0.2
Summary: AWS Cloudformation deployer. 
Home-page: https://github.com/flou/brume
Author: Lou Ferrand, Jerome Guibert
Author-email: ferrand@ekino.com, jguibert@gmail.com
License: MIT
Download-URL: https://github.com/flou/brume/repository/archive.tar.gz?ref=2.0.2
Keywords: AWS,CloudFormation
Platform: UNKNOWN
Classifier: Development Status :: 5 - Production/Stable
Classifier: Environment :: Console
Classifier: Intended Audience :: Developers
Classifier: Operating System :: POSIX
Classifier: Operating System :: MacOS
Classifier: Operating System :: Unix
Classifier: Programming Language :: Python
Classifier: Programming Language :: Python :: 3.4
Classifier: Programming Language :: Python :: 3.5
Classifier: Programming Language :: Python :: 3.6
Classifier: Programming Language :: Python :: 3.7
Classifier: Topic :: Software Development :: Libraries :: Python Modules
Requires-Dist: boto3 (>=1.9.145)
Requires-Dist: crayons (==0.2.0)
Requires-Dist: click (>=7.0)
Requires-Dist: PyYAML (>=5.1)
Requires-Dist: Jinja2 (==2.10.1)
Requires-Dist: pytz (>=2019.1)
Requires-Dist: delegator.py (>=0.1.1)
Requires-Dist: six (>=1.12.0)
